dhllinalg/__init__.py
dhllinalg/bla.cpython-38-darwin.so
dhllinalg/include/matrix.h
dhllinalg/include/taskmanager.h
dhllinalg/include/timer.h
dhllinalg/include/vector.h
dhllinalg-0.1.1.dist-info/LICENSE
dhllinalg-0.1.1.dist-info/METADATA
dhllinalg-0.1.1.dist-info/WHEEL
dhllinalg-0.1.1.dist-info/top_level.txt
dhllinalg-0.1.1.dist-info/RECORD
