Metadata-Version: 2.1
Name: dhllinalg
Version: 0.1.1
Summary: Basic Linear Algebra in C++ (TU Vienna - ASC)
Home-page: https://github.com/DHL-ASC/DHL-LinAlg
Author: DHL-Team
License: LGPL2.1
Platform: UNKNOWN
Classifier: Development Status :: 3 - Alpha
Classifier: Intended Audience :: Science/Research
Classifier: Programming Language :: Python :: 3
Classifier: Programming Language :: Python :: 3.8
Classifier: Programming Language :: Python :: 3.9
Classifier: Programming Language :: Python :: 3.10
Classifier: Programming Language :: Python :: 3.11
Classifier: Programming Language :: Python :: 3.12
Requires-Dist: setuptools >=42
Requires-Dist: scikit-build >=0.13
Requires-Dist: pybind11
Provides-Extra: all
Requires-Dist: pytest ; extra == 'all'
Requires-Dist: numpy ; extra == 'all'
Requires-Dist: sphinx ; extra == 'all'
Requires-Dist: myst-nb ; extra == 'all'
Requires-Dist: pandocfilters ; extra == 'all'
Provides-Extra: docs
Requires-Dist: sphinx ; extra == 'docs'
Requires-Dist: myst-nb ; extra == 'docs'
Requires-Dist: pandocfilters ; extra == 'docs'
Provides-Extra: test
Requires-Dist: pytest ; extra == 'test'
Requires-Dist: numpy ; extra == 'test'
